hydrosignatures/__init__.py
hydrosignatures/baseflow.py
hydrosignatures/exceptions.py
hydrosignatures/hydrosignatures.py
hydrosignatures/plot.py
hydrosignatures/print_versions.py
hydrosignatures/py.typed
hydrosignatures-0.19.3.dist-info/METADATA
hydrosignatures-0.19.3.dist-info/WHEEL
hydrosignatures-0.19.3.dist-info/licenses/AUTHORS.rst
hydrosignatures-0.19.3.dist-info/licenses/LICENSE
hydrosignatures-0.19.3.dist-info/RECORD
