Metadata-Version: 2.4
Name: hydrosignatures
Version: 0.19.3
Summary: A collection of tools for computing hydrological signatures
Project-URL: Changelog, https://docs.hyriver.io/changelogs/hydrosignatures.html
Project-URL: CI, https://github.com/hyriver/hydrosignatures/actions
Project-URL: Homepage, https://docs.hyriver.io/readme/hydrosignatures.html
Project-URL: Issues, https://github.com/hyriver/hydrosignatures/issues
Author-email: Taher Chegini <cheginit@gmail.com>
License: MIT
License-File: AUTHORS.rst
License-File: LICENSE
Classifier: Development Status :: 4 - Beta
Classifier: Intended Audience :: Science/Research
Classifier: License :: OSI Approved :: MIT License
Classifier: Operating System :: OS Independent
Classifier: Programming Language :: Python
Classifier: Programming Language :: Python :: 3 :: Only
Classifier: Programming Language :: Python :: 3.9
Classifier: Programming Language :: Python :: 3.10
Classifier: Programming Language :: Python :: 3.11
Classifier: Programming Language :: Python :: 3.12
Classifier: Programming Language :: Python :: 3.13
Classifier: Topic :: Scientific/Engineering
Classifier: Topic :: Scientific/Engineering :: GIS
Classifier: Topic :: Scientific/Engineering :: Hydrology
Classifier: Typing :: Typed
Requires-Python: >=3.9
Requires-Dist: numpy>=2
Requires-Dist: pandas>=1
Requires-Dist: scipy
Requires-Dist: xarray>=2024.7
Provides-Extra: jit
Requires-Dist: numba>=0.57; extra == 'jit'
Requires-Dist: numbagg; extra == 'jit'
Provides-Extra: plot
Requires-Dist: matplotlib; extra == 'plot'
Provides-Extra: test
Requires-Dist: pytest-cov; extra == 'test'
Requires-Dist: pytest-sugar; extra == 'test'
